{
    "id": 117600693,
    "name": "steves lava chicken",
    "author": "blightedcoconut",
    "creators": [],
    "verifier": "pixelfactorial",
    "verification": "https://youtu.be/jdh89IUC9_M",
    "percentToQualify": "100",
    "handcam": 0,
    "device": "Any",
    "fps": "CBF",
    "records": [
        {
            "user": "ywuChaos",
            "link": "https://youtu.be/A9zb01vGHmo?si=rqIm4O_IXmJCKAHc&t=48",
            "hz": "CBF",
            "percent": 100
        },
        {
            "user": "IsntAdam",
            "link": "https://www.youtube.com/watch?v=VKDvM18xjZk",
            "hz": "CBF",
            "percent": 100
        },
        {
        "user": "loooookkk",
        "link": "https://youtu.be/-m8VcZnAdzc?si=n2Ds-MQJbkLvsB3A&t=130",
            "hz": "CBF",
            "percent": 100
        },
        {
            "user": "Astroguy",
            "link": "https://www.youtube.com/watch?v=V-qsqQ2HMj4",
            "hz": "CBF",
            "percent": 100
        }
    ]
}
